kafka_replay_cli/__init__.py
kafka_replay_cli/cli.py
kafka_replay_cli/dump.py
kafka_replay_cli/query.py
kafka_replay_cli/replay.py
kafka_replay_cli/schema.py
kafka_replay_cli/utils.py
kafka_replay_cli-0.4.0.dist-info/licenses/LICENSE.md
kafka_replay_cli-0.4.0.dist-info/METADATA
kafka_replay_cli-0.4.0.dist-info/WHEEL
kafka_replay_cli-0.4.0.dist-info/entry_points.txt
kafka_replay_cli-0.4.0.dist-info/top_level.txt
kafka_replay_cli-0.4.0.dist-info/RECORD
