Metadata-Version: 2.4
Name: kafka-replay-cli
Version: 0.4.0
Summary: A CLI tool to dump and replay Kafka messages using Parquet
Author: Konstantinas Mamonas
License: MIT
License-File: LICENSE.md
Requires-Dist: typer
Requires-Dist: confluent-kafka
Requires-Dist: pyarrow
Requires-Dist: duckdb
Requires-Dist: pandas
Requires-Dist: python-dateutil
Provides-Extra: dev
Requires-Dist: build; extra == "dev"
Requires-Dist: twine; extra == "dev"
Requires-Dist: pytest; extra == "dev"
Requires-Dist: black; extra == "dev"
Requires-Dist: ruff; extra == "dev"
Dynamic: license-file
